flyline/__init__.py
flyline/airattributes.py
flyline/airfare.py
flyline/airresources.py
flyline/airschedules.py
flyline/airseatmaps.py
flyline/errors.py
flyline/flylinebaseclient.py
flyline/flylineclient.py
flyline/schemas.py
flyline/types.py
flyline-0.1.4.dist-info/WHEEL
flyline-0.1.4.dist-info/METADATA
flyline-0.1.4.dist-info/RECORD
