Metadata-Version: 2.1
Name: flyline
Version: 0.1.4
Summary: Flyline Client Libraray
Author: Flyline Development Team
Author-email: development@flyline.io
Requires-Python: >=3.8,<4.0
Classifier: Programming Language :: Python :: 3
Classifier: Programming Language :: Python :: 3.8
Classifier: Programming Language :: Python :: 3.9
Requires-Dist: aiohttp (>=3.7.4,<4.0.0)
